langchain_model_profiles/__init__.py
langchain_model_profiles/_data_loader.py
langchain_model_profiles/model_profile.py
langchain_model_profiles/data/ATTRIBUTION.txt
langchain_model_profiles/data/models.json
langchain_model_profiles/data/augmentations/README.md
langchain_model_profiles/data/augmentations/models/openai/gpt-3.5-turbo.toml
langchain_model_profiles/data/augmentations/providers/amazon-bedrock.toml
langchain_model_profiles/data/augmentations/providers/anthropic.toml
langchain_model_profiles/data/augmentations/providers/google.toml
langchain_model_profiles/data/augmentations/providers/google_vertexai.toml
langchain_model_profiles/data/augmentations/providers/openai.toml
langchain_model_profiles-0.0.4.dist-info/METADATA
langchain_model_profiles-0.0.4.dist-info/WHEEL
langchain_model_profiles-0.0.4.dist-info/RECORD
