Metadata-Version: 2.4
Name: langchain-model-profiles
Version: 0.0.4
Summary: Centralized reference of LLM capabilities.
Project-URL: Homepage, https://docs.langchain.com/
Project-URL: Documentation, https://reference.langchain.com/python/langchain_model_profiles/
Project-URL: Source, https://github.com/langchain-ai/langchain/tree/master/libs/model-profiles
Project-URL: Twitter, https://x.com/LangChainAI
Project-URL: Slack, https://www.langchain.com/join-community
Project-URL: Reddit, https://www.reddit.com/r/LangChain/
License: MIT
Requires-Python: <4.0.0,>=3.10.0
Requires-Dist: tomli<3.0.0,>=2.0.0; python_version < '3.11'
Requires-Dist: typing-extensions<5.0.0,>=4.7.0
